pheval_lirical/__init__.py
pheval_lirical/cli.py
pheval_lirical/post_process/__init__.py
pheval_lirical/post_process/post_process.py
pheval_lirical/post_process/post_process_results_format.py
pheval_lirical/prepare/__init__.py
pheval_lirical/prepare/prepare_commands.py
pheval_lirical/prepare/prepare_manual_commands.py
pheval_lirical/prepare/prepare_phenopacket_commands.py
pheval_lirical/run/__init__.py
pheval_lirical/run/run.py
pheval_lirical/runner.py
pheval_lirical/tool_specific_configuration_parser.py
pheval_lirical-0.2.3.dist-info/METADATA
pheval_lirical-0.2.3.dist-info/WHEEL
pheval_lirical-0.2.3.dist-info/entry_points.txt
pheval_lirical-0.2.3.dist-info/RECORD
