Metadata-Version: 2.4
Name: pheval_lirical
Version: 0.2.3
Summary: 
Author: Yasemin Bridges
Author-email: y.bridges@qmul.ac.uk
Requires-Python: >=3.10,<4.0.0
Classifier: Programming Language :: Python :: 3
Classifier: Programming Language :: Python :: 3.10
Classifier: Programming Language :: Python :: 3.11
Classifier: Programming Language :: Python :: 3.12
Classifier: Programming Language :: Python :: 3.13
Classifier: Programming Language :: Python :: 3.14
Requires-Dist: click (>=8.1.3,<9.0.0)
Requires-Dist: docker (>=6.0.1,<7.0.0)
Requires-Dist: google (>=3.0.0,<4.0.0)
Requires-Dist: oaklib (>=0.5.6)
Requires-Dist: phenopackets (>=2.0.2,<3.0.0)
Requires-Dist: pheval (>=0.5.2,<0.6.0)
Requires-Dist: pyaml (>=21.10.1,<22.0.0)
